hoardy_web_sas.py
hoardy_web_sas-1.9.0.dist-info/METADATA
hoardy_web_sas-1.9.0.dist-info/WHEEL
hoardy_web_sas-1.9.0.dist-info/entry_points.txt
hoardy_web_sas-1.9.0.dist-info/top_level.txt
hoardy_web_sas-1.9.0.dist-info/RECORD
